aimbase/__init__.py
aimbase/core/__init__.py
aimbase/core/config.py
aimbase/core/constants.py
aimbase/core/minio.py
aimbase/crud/__init__.py
aimbase/crud/base.py
aimbase/crud/sentence_transformers_vector.py
aimbase/crud/vector.py
aimbase/db/__init__.py
aimbase/db/base.py
aimbase/db/vector.py
aimbase/dependencies.py
aimbase/initializer.py
aimbase/routers/__init__.py
aimbase/routers/sentence_transformers_router.py
aimbase/services/__init__.py
aimbase/services/base.py
aimbase/services/cross_encoder_inference.py
aimbase/services/sentence_transformers_inference.py
aimbase-0.0.10.dist-info/LICENSE
aimbase-0.0.10.dist-info/METADATA
aimbase-0.0.10.dist-info/WHEEL
aimbase-0.0.10.dist-info/RECORD
