Metadata-Version: 2.1
Name: aimbase
Version: 0.0.10
Summary: Declarative, instant REST APIs for base AI Models based on instarest, a FastAPI, Pydantic, SQLAlchemy, and PostgreSQL library, and MinIO.
Author: Eric Robinson
Requires-Python: >=3.11,<3.12
Classifier: Programming Language :: Python :: 3
Classifier: Programming Language :: Python :: 3.11
Requires-Dist: instarest (>=0.0.13)
Requires-Dist: minio (>=7.1.15,<8.0.0)
Requires-Dist: openai (>=1.3.8,<2.0.0)
Requires-Dist: pgvector (>=0.2.3,<0.3.0)
Requires-Dist: tqdm (>=4.65.0,<5.0.0)
